inprompt.py
inprompt-1.6.2.dist-info/METADATA
inprompt-1.6.2.dist-info/WHEEL
inprompt-1.6.2.dist-info/entry_points.txt
inprompt-1.6.2.dist-info/licenses/LICENSE
inprompt-1.6.2.dist-info/RECORD
