Metadata-Version: 2.4
Name: inprompt
Version: 1.6.2
Summary: A tiny CLI that outputs files as Markdown-formatted code blocks.
Author: Dominik Roblek
License-Expression: MIT
License-File: LICENSE
Keywords: code,fence,formatting,markdown,prompt
Classifier: License :: OSI Approved :: MIT License
Classifier: Programming Language :: Python :: 3
Classifier: Topic :: Utilities
Requires-Python: >=3.9
Requires-Dist: absl-py
Requires-Dist: loguru
